faifah/__init__.py
faifah/ieee_test_system.py
faifah/load_profile.py
faifah/lumache.py
faifah/test.py
faifah-0.0.17.dist-info/LICENSE
faifah-0.0.17.dist-info/METADATA
faifah-0.0.17.dist-info/WHEEL
faifah-0.0.17.dist-info/top_level.txt
faifah-0.0.17.dist-info/RECORD
