Metadata-Version: 2.1
Name: faifah
Version: 0.0.17
Summary: DESCRIPTION
Author: AKANIT KWANGKAEW
Author-email: <akanitk84@gmail.com>
Keywords: python,power system,voltage stability
Classifier: Development Status :: 1 - Planning
Classifier: Intended Audience :: Developers
Classifier: Programming Language :: Python :: 3
Classifier: Operating System :: Unix
Classifier: Operating System :: MacOS :: MacOS X
Classifier: Operating System :: Microsoft :: Windows
Classifier: License :: OSI Approved :: MIT License
License-File: LICENSE
Requires-Dist: pypsa
Requires-Dist: numpy
Requires-Dist: pandas
Requires-Dist: colorama
Requires-Dist: termcolor
